flake8_jungle/__init__.py
flake8_jungle/checker.py
flake8_jungle/rules/__init__.py
flake8_jungle/rules/base.py
flake8_jungle/rules/jg01_model_content_order.py
flake8_jungle/rules/jg02_model_form.py
flake8_jungle/rules/jg03_model_fields.py
flake8_jungle/rules/jg04_try_except_pass.py
flake8_jungle/rules/jg05_complicated_condition.py
flake8_jungle/rules/jg06_function_too_long.py
flake8_jungle/rules/jg07_model_too_long.py
flake8_jungle/rules/jg08_import_inside_function.py
flake8_jungle/rules/jg09_logging_format.py
flake8_jungle/rules/jg10_too_much_patching.py
flake8_jungle/rules/jg11_structlog_format.py
flake8_jungle-1.0.7.dist-info/entry_points.txt
flake8_jungle-1.0.7.dist-info/WHEEL
flake8_jungle-1.0.7.dist-info/METADATA
flake8_jungle-1.0.7.dist-info/RECORD
