Metadata-Version: 2.1
Name: flake8-jungle
Version: 1.0.7
Summary: Plugin to lint various issues in code.
Home-page: https://github.com/TwistoPayments/flake8-jungle
License: GPL-3.0-or-later
Keywords: flake8,lint
Author: Twisto Platform Team
Author-email: platform@twisto.cz
Requires-Python: >=3.8,<4.0
Classifier: Framework :: Flake8
Classifier: License :: OSI Approved :: GNU General Public License v3 or later (GPLv3+)
Classifier: License :: OSI Approved :: MIT License
Classifier: Programming Language :: Python
Classifier: Programming Language :: Python :: 3
Classifier: Programming Language :: Python :: 3.8
Classifier: Programming Language :: Python :: 3.9
Classifier: Programming Language :: Python :: 3.10
Classifier: Programming Language :: Python :: 3
Classifier: Programming Language :: Python :: 3.10
Classifier: Programming Language :: Python :: 3.8
Classifier: Programming Language :: Python :: 3.9
Classifier: Topic :: Software Development :: Libraries :: Python Modules
Classifier: Topic :: Software Development :: Quality Assurance
Requires-Dist: flake8 (>=3.8.4)
Project-URL: Repository, https://github.com/TwistoPayments/flake8-jungle
